httpx_system_certs.pth
httpx_system_certs/__init__.py
httpx_system_certs/patch.py
httpx_system_certs-1.0.0.dist-info/licenses/LICENSE
httpx_system_certs-1.0.0.dist-info/METADATA
httpx_system_certs-1.0.0.dist-info/WHEEL
httpx_system_certs-1.0.0.dist-info/top_level.txt
httpx_system_certs-1.0.0.dist-info/RECORD
