Metadata-Version: 2.4
Name: httpx_system_certs
Version: 1.0.0
Summary: Patch httpx to use system certificates authority bundles by default
Home-page: https://github.com/Baltoch/httpx-system-certs
Author: Balthazar LEBRETON
Author-email: balthazar.lebreton@gmail.com
License: MIT
License-File: LICENSE
Requires-Dist: truststore
Requires-Dist: httpx
Dynamic: author
Dynamic: author-email
Dynamic: description
Dynamic: home-page
Dynamic: license
Dynamic: license-file
Dynamic: requires-dist
Dynamic: summary
